langchain_fmp_data/__init__.py
langchain_fmp_data/agent.py
langchain_fmp_data/py.typed
langchain_fmp_data/toolkits.py
langchain_fmp_data/tools.py
langchain_fmp_data-0.1.1.dist-info/LICENSE
langchain_fmp_data-0.1.1.dist-info/METADATA
langchain_fmp_data-0.1.1.dist-info/WHEEL
langchain_fmp_data-0.1.1.dist-info/RECORD
