Metadata-Version: 2.3
Name: langchain-fmp-data
Version: 0.1.1
Summary: An integration package connecting FmpData and LangChain
License: MIT
Requires-Python: >=3.10,<3.14
Classifier: License :: OSI Approved :: MIT License
Classifier: Programming Language :: Python :: 3
Classifier: Programming Language :: Python :: 3.10
Classifier: Programming Language :: Python :: 3.11
Classifier: Programming Language :: Python :: 3.12
Classifier: Programming Language :: Python :: 3.13
Requires-Dist: faiss-cpu (>=1.9.0.post1,<2.0.0)
Requires-Dist: fmp-data[langchain] (>=1.0.0,<2.0.0)
Requires-Dist: langchain (>=0.3.14,<0.4.0)
Requires-Dist: langchain-community (>=0.3.14,<0.4.0)
Requires-Dist: langchain-core (>=0.3.15,<0.4.0)
Requires-Dist: langchain-openai (>=0.3.0,<0.4.0)
Requires-Dist: langgraph (>=0.2.62,<0.3.0)
Project-URL: Repository, https://github.com/MehdiZare/langchain-fmp-data
Project-URL: Source Code, https://github.com/MehdiZare/langchain-fmp-data
